LICENSE
LICENSE.original
README.md
netdevsnmp/__init__.py
netdevsnmp/errors.py
netdevsnmp/hostinfo/__init__.py
netdevsnmp/hostinfo/collect.py
netdevsnmp/hostinfo/device.py
netdevsnmp/hostinfo/version.py
netdevsnmp/oids/__init__.py
netdevsnmp/snmp.py
netdevsnmp/vendors/__init__.py
netdevsnmp/vendors/airespace/__init__.py
netdevsnmp/vendors/airespace/oids.py
netdevsnmp/vendors/alcatel/__init__.py
netdevsnmp/vendors/alcatel/versions.py
netdevsnmp/vendors/arbor/__init__.py
netdevsnmp/vendors/arbor/versions.py
netdevsnmp/vendors/arista/__init__.py
netdevsnmp/vendors/arista/versions.py
netdevsnmp/vendors/cisco/__init__.py
netdevsnmp/vendors/cisco/cdp.py
netdevsnmp/vendors/cisco/oids.py
netdevsnmp/vendors/cisco/versions.py
netdevsnmp/vendors/ericsson/__init__.py
netdevsnmp/vendors/ericsson/versions.py
netdevsnmp/vendors/extreme/__init__.py
netdevsnmp/vendors/extreme/versions.py
netdevsnmp/vendors/hpe/__init__.py
netdevsnmp/vendors/hpe/versions.py
netdevsnmp/vendors/huawei/__init__.py
netdevsnmp/vendors/huawei/versions.py
netdevsnmp/vendors/juniper/__init__.py
netdevsnmp/vendors/juniper/versions.py
netdevsnmp/vendors/mappings.py
netdevsnmp/vendors/metamako/__init__.py
netdevsnmp/vendors/metamako/versions.py
netdevsnmp/vendors/synology/__init__.py
netdevsnmp/vendors/synology/oids.py
netdevsnmp/vendors/synology/versions.py
netdevsnmp-1.0.0.dist-info/LICENSE.original
netdevsnmp-1.0.0.dist-info/LICENSE
netdevsnmp-1.0.0.dist-info/WHEEL
netdevsnmp-1.0.0.dist-info/METADATA
netdevsnmp-1.0.0.dist-info/RECORD
